arc_agi_dsl/__init__.py
arc_agi_dsl/_utils.py
arc_agi_dsl/d8_symmetry/__init__.py
arc_agi_dsl/d8_symmetry/primitives.py
arc_agi_dsl/d8_symmetry/rule_set.py
arc_agi_dsl-0.0.3.dist-info/METADATA
arc_agi_dsl-0.0.3.dist-info/WHEEL
arc_agi_dsl-0.0.3.dist-info/RECORD
