Metadata-Version: 2.4
Name: arc-agi-dsl
Version: 0.0.3
Requires-Python: >=3.10
Requires-Dist: arc-agi-core
